[
	{
		"tm" : 1720857546984,
		"x" : 161,
		"y" : 1038
	},
	{
		"tm" : 1720857547045,
		"x" : 215,
		"y" : 985
	},
	{
		"tm" : 1720857547097,
		"x" : 315,
		"y" : 902
	},
	{
		"tm" : 1720857547153,
		"x" : 474,
		"y" : 774
	},
	{
		"tm" : 1720857547210,
		"x" : 616,
		"y" : 663
	},
	{
		"tm" : 1720857547265,
		"x" : 670,
		"y" : 631
	},
	{
		"tm" : 1720857547321,
		"x" : 702,
		"y" : 615
	},
	{
		"tm" : 1720857547377,
		"x" : 743,
		"y" : 608
	},
	{
		"tm" : 1720857547435,
		"x" : 880,
		"y" : 579
	},
	{
		"tm" : 1720857547489,
		"x" : 1056,
		"y" : 545
	},
	{
		"tm" : 1720857547540,
		"x" : 1106,
		"y" : 530
	},
	{
		"tm" : 1720857547945,
		"x" : 1110,
		"y" : 547
	},
	{
		"tm" : 1720857548005,
		"x" : 1076,
		"y" : 595
	},
	{
		"tm" : 1720857548057,
		"x" : 1030,
		"y" : 674
	},
	{
		"tm" : 1720857548113,
		"x" : 1009,
		"y" : 738
	},
	{
		"tm" : 1720857548170,
		"x" : 1012,
		"y" : 762
	},
	{
		"tm" : 1720857549185,
		"x" : 1000,
		"y" : 749
	},
	{
		"tm" : 1720857549241,
		"x" : 952,
		"y" : 730
	},
	{
		"tm" : 1720857549297,
		"x" : 923,
		"y" : 718
	},
	{
		"tm" : 1720857549553,
		"x" : 906,
		"y" : 725
	},
	{
		"tm" : 1720857549681,
		"x" : 894,
		"y" : 736
	},
	{
		"tm" : 1720857549820,
		"x" : 886,
		"y" : 752
	},
	{
		"tm" : 1720857549873,
		"x" : 879,
		"y" : 768
	},
	{
		"tm" : 1720857549929,
		"x" : 864,
		"y" : 791
	},
	{
		"tm" : 1720857549985,
		"x" : 828,
		"y" : 822
	},
	{
		"tm" : 1720857550041,
		"x" : 766,
		"y" : 860
	},
	{
		"tm" : 1720857550097,
		"x" : 723,
		"y" : 893
	},
	{
		"tm" : 1720857550153,
		"x" : 704,
		"y" : 917
	},
	{
		"tm" : 1720857550420,
		"x" : 710,
		"y" : 902
	},
	{
		"tm" : 1720857550569,
		"x" : 728,
		"y" : 909
	},
	{
		"tm" : 1720857554896,
		"x" : 726,
		"y" : 893
	},
	{
		"tm" : 1720857555464,
		"x" : 741,
		"y" : 887
	},
	{
		"tm" : 1720857556136,
		"x" : 756,
		"y" : 881
	},
	{
		"tm" : 1720857556256,
		"x" : 771,
		"y" : 874
	},
	{
		"tm" : 1720857556320,
		"x" : 786,
		"y" : 868
	},
	{
		"tm" : 1720857556392,
		"x" : 802,
		"y" : 862
	},
	{
		"tm" : 1720857556448,
		"x" : 823,
		"y" : 849
	},
	{
		"tm" : 1720857556505,
		"x" : 859,
		"y" : 828
	},
	{
		"tm" : 1720857556560,
		"x" : 913,
		"y" : 788
	},
	{
		"tm" : 1720857556616,
		"x" : 961,
		"y" : 749
	},
	{
		"tm" : 1720857556672,
		"x" : 986,
		"y" : 716
	},
	{
		"tm" : 1720857556730,
		"x" : 1004,
		"y" : 694
	},
	{
		"tm" : 1720857556808,
		"x" : 1014,
		"y" : 681
	},
	{
		"tm" : 1720857558672,
		"x" : 999,
		"y" : 689
	},
	{
		"tm" : 1720857558880,
		"x" : 984,
		"y" : 697
	},
	{
		"tm" : 1720857559040,
		"x" : 969,
		"y" : 705
	},
	{
		"tm" : 1720857559272,
		"x" : 958,
		"y" : 691
	},
	{
		"tm" : 1720857559328,
		"x" : 949,
		"y" : 632
	},
	{
		"tm" : 1720857559385,
		"x" : 949,
		"y" : 561
	},
	{
		"tm" : 1720857559440,
		"x" : 954,
		"y" : 513
	},
	{
		"tm" : 1720857559496,
		"x" : 969,
		"y" : 444
	},
	{
		"tm" : 1720857559552,
		"x" : 1006,
		"y" : 347
	},
	{
		"tm" : 1720857559610,
		"x" : 1029,
		"y" : 270
	},
	{
		"tm" : 1720857560241,
		"x" : 1013,
		"y" : 271
	},
	{
		"tm" : 1720857560297,
		"x" : 991,
		"y" : 278
	},
	{
		"tm" : 1720857560561,
		"x" : 973,
		"y" : 284
	},
	{
		"tm" : 1720857560616,
		"x" : 957,
		"y" : 290
	},
	{
		"tm" : 1720857560961,
		"x" : 937,
		"y" : 288
	},
	{
		"tm" : 1720857561017,
		"x" : 898,
		"y" : 281
	},
	{
		"tm" : 1720857561241,
		"x" : 888,
		"y" : 295
	},
	{
		"tm" : 1720857561617,
		"x" : 888,
		"y" : 313
	},
	{
		"tm" : 1720857561673,
		"x" : 889,
		"y" : 350
	},
	{
		"tm" : 1720857561729,
		"x" : 888,
		"y" : 375
	},
	{
		"tm" : 1720857561873,
		"x" : 887,
		"y" : 356
	},
	{
		"tm" : 1720857561929,
		"x" : 891,
		"y" : 327
	},
	{
		"tm" : 1720857562425,
		"x" : 886,
		"y" : 343
	},
	{
		"tm" : 1720857562649,
		"x" : 891,
		"y" : 359
	},
	{
		"tm" : 1720857562721,
		"x" : 903,
		"y" : 370
	},
	{
		"tm" : 1720857562777,
		"x" : 944,
		"y" : 370
	},
	{
		"tm" : 1720857562833,
		"x" : 1010,
		"y" : 330
	},
	{
		"tm" : 1720857562889,
		"x" : 1053,
		"y" : 282
	},
	{
		"tm" : 1720857562945,
		"x" : 1083,
		"y" : 256
	},
	{
		"tm" : 1720857563297,
		"x" : 1088,
		"y" : 240
	},
	{
		"tm" : 1720857563401,
		"x" : 1088,
		"y" : 224
	},
	{
		"tm" : 1720857563497,
		"x" : 1084,
		"y" : 208
	},
	{
		"tm" : 1720857563876,
		"x" : 1085,
		"y" : 192
	},
	{
		"tm" : 1720857564017,
		"x" : 1087,
		"y" : 176
	},
	{
		"tm" : 1720857564073,
		"x" : 1084,
		"y" : 151
	},
	{
		"tm" : 1720857564457,
		"x" : 1070,
		"y" : 161
	},
	{
		"tm" : 1720857564921,
		"x" : 1084,
		"y" : 179
	},
	{
		"tm" : 1720857564977,
		"x" : 1177,
		"y" : 219
	},
	{
		"tm" : 1720857565033,
		"x" : 1249,
		"y" : 234
	},
	{
		"tm" : 1720857565289,
		"x" : 1263,
		"y" : 242
	},
	{
		"tm" : 1720857565633,
		"x" : 1270,
		"y" : 257
	},
	{
		"tm" : 1720857565697,
		"x" : 1276,
		"y" : 272
	},
	{
		"tm" : 1720857565777,
		"x" : 1283,
		"y" : 287
	},
	{
		"tm" : 1720857565840,
		"x" : 1289,
		"y" : 303
	},
	{
		"tm" : 1720857565905,
		"x" : 1297,
		"y" : 318
	},
	{
		"tm" : 1720857565960,
		"x" : 1308,
		"y" : 335
	},
	{
		"tm" : 1720857566017,
		"x" : 1325,
		"y" : 363
	},
	{
		"tm" : 1720857566073,
		"x" : 1351,
		"y" : 398
	},
	{
		"tm" : 1720857566129,
		"x" : 1398,
		"y" : 438
	},
	{
		"tm" : 1720857566185,
		"x" : 1474,
		"y" : 472
	},
	{
		"tm" : 1720857566241,
		"x" : 1557,
		"y" : 481
	},
	{
		"tm" : 1720857566297,
		"x" : 1612,
		"y" : 470
	},
	{
		"tm" : 1720857566489,
		"x" : 1587,
		"y" : 465
	},
	{
		"tm" : 1720857566546,
		"x" : 1474,
		"y" : 458
	},
	{
		"tm" : 1720857566657,
		"x" : 1447,
		"y" : 457
	},
	{
		"tm" : 1720857567105,
		"x" : 1467,
		"y" : 448
	},
	{
		"tm" : 1720857567160,
		"x" : 1535,
		"y" : 409
	},
	{
		"tm" : 1720857567545,
		"x" : 1517,
		"y" : 414
	},
	{
		"tm" : 1720857567601,
		"x" : 1473,
		"y" : 425
	},
	{
		"tm" : 1720857567760,
		"x" : 1453,
		"y" : 426
	},
	{
		"tm" : 1720857567817,
		"x" : 1396,
		"y" : 432
	},
	{
		"tm" : 1720857567955,
		"x" : 1374,
		"y" : 433
	},
	{
		"tm" : 1720857568009,
		"x" : 1306,
		"y" : 424
	},
	{
		"tm" : 1720857568113,
		"x" : 1288,
		"y" : 422
	},
	{
		"tm" : 1720857568169,
		"x" : 1159,
		"y" : 369
	},
	{
		"tm" : 1720857568225,
		"x" : 1058,
		"y" : 327
	},
	{
		"tm" : 1720857568361,
		"x" : 1059,
		"y" : 344
	},
	{
		"tm" : 1720857568450,
		"x" : 1052,
		"y" : 362
	},
	{
		"tm" : 1720857568521,
		"x" : 1039,
		"y" : 378
	},
	{
		"tm" : 1720857568577,
		"x" : 1028,
		"y" : 410
	},
	{
		"tm" : 1720857569057,
		"x" : 1048,
		"y" : 416
	},
	{
		"tm" : 1720857569113,
		"x" : 1241,
		"y" : 454
	},
	{
		"tm" : 1720857569233,
		"x" : 1297,
		"y" : 465
	},
	{
		"tm" : 1720857569754,
		"x" : 1303,
		"y" : 481
	},
	{
		"tm" : 1720857569952,
		"x" : 1287,
		"y" : 489
	},
	{
		"tm" : 1720857570120,
		"x" : 1271,
		"y" : 493
	},
	{
		"tm" : 1720857570176,
		"x" : 1222,
		"y" : 489
	},
	{
		"tm" : 1720857570234,
		"x" : 1143,
		"y" : 472
	},
	{
		"tm" : 1720857570288,
		"x" : 1063,
		"y" : 457
	},
	{
		"tm" : 1720857570344,
		"x" : 946,
		"y" : 434
	},
	{
		"tm" : 1720857570400,
		"x" : 757,
		"y" : 398
	},
	{
		"tm" : 1720857570504,
		"x" : 728,
		"y" : 397
	},
	{
		"tm" : 1720857570640,
		"x" : 710,
		"y" : 392
	},
	{
		"tm" : 1720857570696,
		"x" : 657,
		"y" : 366
	},
	{
		"tm" : 1720857570944,
		"x" : 640,
		"y" : 364
	},
	{
		"tm" : 1720857571104,
		"x" : 624,
		"y" : 352
	},
	{
		"tm" : 1720857571160,
		"x" : 585,
		"y" : 293
	},
	{
		"tm" : 1720857571216,
		"x" : 568,
		"y" : 265
	},
	{
		"tm" : 1720857571656,
		"x" : 588,
		"y" : 266
	},
	{
		"tm" : 1720857571712,
		"x" : 816,
		"y" : 313
	},
	{
		"tm" : 1720857571768,
		"x" : 1152,
		"y" : 409
	},
	{
		"tm" : 1720857571824,
		"x" : 1209,
		"y" : 442
	},
	{
		"tm" : 1720857571880,
		"x" : 1224,
		"y" : 456
	},
	{
		"tm" : 1720857571936,
		"x" : 1240,
		"y" : 470
	},
	{
		"tm" : 1720857572128,
		"x" : 1235,
		"y" : 486
	},
	{
		"tm" : 1720857572184,
		"x" : 1204,
		"y" : 492
	},
	{
		"tm" : 1720857572264,
		"x" : 1187,
		"y" : 495
	},
	{
		"tm" : 1720857572320,
		"x" : 1166,
		"y" : 499
	},
	{
		"tm" : 1720857572376,
		"x" : 1055,
		"y" : 499
	},
	{
		"tm" : 1720857572432,
		"x" : 892,
		"y" : 499
	},
	{
		"tm" : 1720857572488,
		"x" : 721,
		"y" : 497
	},
	{
		"tm" : 1720857572544,
		"x" : 619,
		"y" : 484
	},
	{
		"tm" : 1720857572600,
		"x" : 566,
		"y" : 469
	},
	{
		"tm" : 1720857572904,
		"x" : 551,
		"y" : 461
	},
	{
		"tm" : 1720857573440,
		"x" : 566,
		"y" : 452
	},
	{
		"tm" : 1720857573888,
		"x" : 581,
		"y" : 444
	},
	{
		"tm" : 1720857573960,
		"x" : 597,
		"y" : 447
	},
	{
		"tm" : 1720857574256,
		"x" : 612,
		"y" : 441
	},
	{
		"tm" : 1720857574440,
		"x" : 629,
		"y" : 442
	},
	{
		"tm" : 1720857574496,
		"x" : 676,
		"y" : 450
	},
	{
		"tm" : 1720857574552,
		"x" : 786,
		"y" : 437
	},
	{
		"tm" : 1720857574608,
		"x" : 953,
		"y" : 404
	},
	{
		"tm" : 1720857574664,
		"x" : 1055,
		"y" : 389
	},
	{
		"tm" : 1720857574721,
		"x" : 1117,
		"y" : 394
	},
	{
		"tm" : 1720857575080,
		"x" : 1126,
		"y" : 408
	},
	{
		"tm" : 1720857575176,
		"x" : 1112,
		"y" : 420
	},
	{
		"tm" : 1720857575232,
		"x" : 1067,
		"y" : 437
	},
	{
		"tm" : 1720857575288,
		"x" : 932,
		"y" : 464
	},
	{
		"tm" : 1720857575344,
		"x" : 805,
		"y" : 489
	},
	{
		"tm" : 1720857575400,
		"x" : 753,
		"y" : 506
	},
	{
		"tm" : 1720857575568,
		"x" : 740,
		"y" : 520
	},
	{
		"tm" : 1720857575624,
		"x" : 733,
		"y" : 535
	},
	{
		"tm" : 1720857575736,
		"x" : 720,
		"y" : 546
	},
	{
		"tm" : 1720857575984,
		"x" : 732,
		"y" : 563
	},
	{
		"tm" : 1720857576176,
		"x" : 747,
		"y" : 571
	},
	{
		"tm" : 1720857576386,
		"x" : 763,
		"y" : 566
	},
	{
		"tm" : 1720857576440,
		"x" : 786,
		"y" : 550
	},
	{
		"tm" : 1720857576600,
		"x" : 801,
		"y" : 559
	},
	{
		"tm" : 1720857576656,
		"x" : 801,
		"y" : 584
	},
	{
		"tm" : 1720857576712,
		"x" : 789,
		"y" : 606
	},
	{
		"tm" : 1720857576944,
		"x" : 804,
		"y" : 600
	},
	{
		"tm" : 1720857577001,
		"x" : 829,
		"y" : 590
	},
	{
		"tm" : 1720857577072,
		"x" : 839,
		"y" : 577
	},
	{
		"tm" : 1720857577128,
		"x" : 846,
		"y" : 561
	},
	{
		"tm" : 1720857577184,
		"x" : 876,
		"y" : 518
	},
	{
		"tm" : 1720857577241,
		"x" : 935,
		"y" : 443
	},
	{
		"tm" : 1720857577352,
		"x" : 949,
		"y" : 433
	},
	{
		"tm" : 1720857577409,
		"x" : 984,
		"y" : 426
	},
	{
		"tm" : 1720857577467,
		"x" : 1015,
		"y" : 387
	},
	{
		"tm" : 1720857577842,
		"x" : 999,
		"y" : 394
	},
	{
		"tm" : 1720857578153,
		"x" : 1009,
		"y" : 408
	},
	{
		"tm" : 1720857578209,
		"x" : 1078,
		"y" : 408
	},
	{
		"tm" : 1720857578345,
		"x" : 1103,
		"y" : 408
	},
	{
		"tm" : 1720857578569,
		"x" : 1085,
		"y" : 415
	},
	{
		"tm" : 1720857578625,
		"x" : 975,
		"y" : 439
	},
	{
		"tm" : 1720857578682,
		"x" : 881,
		"y" : 457
	},
	{
		"tm" : 1720857578737,
		"x" : 802,
		"y" : 478
	},
	{
		"tm" : 1720857578802,
		"x" : 769,
		"y" : 493
	},
	{
		"tm" : 1720857579185,
		"x" : 771,
		"y" : 512
	},
	{
		"tm" : 1720857579241,
		"x" : 781,
		"y" : 538
	},
	{
		"tm" : 1720857579377,
		"x" : 763,
		"y" : 537
	},
	{
		"tm" : 1720857579433,
		"x" : 685,
		"y" : 522
	},
	{
		"tm" : 1720857579497,
		"x" : 644,
		"y" : 511
	},
	{
		"tm" : 1720857579801,
		"x" : 645,
		"y" : 527
	},
	{
		"tm" : 1720857579857,
		"x" : 650,
		"y" : 554
	},
	{
		"tm" : 1720857579913,
		"x" : 658,
		"y" : 598
	},
	{
		"tm" : 1720857579969,
		"x" : 662,
		"y" : 622
	},
	{
		"tm" : 1720857580233,
		"x" : 681,
		"y" : 618
	},
	{
		"tm" : 1720857580289,
		"x" : 723,
		"y" : 593
	},
	{
		"tm" : 1720857580347,
		"x" : 753,
		"y" : 550
	},
	{
		"tm" : 1720857580401,
		"x" : 771,
		"y" : 521
	},
	{
		"tm" : 1720857580545,
		"x" : 789,
		"y" : 523
	},
	{
		"tm" : 1720857580602,
		"x" : 844,
		"y" : 522
	},
	{
		"tm" : 1720857580657,
		"x" : 884,
		"y" : 507
	},
	{
		"tm" : 1720857580947,
		"x" : 890,
		"y" : 491
	},
	{
		"tm" : 1720857581169,
		"x" : 902,
		"y" : 477
	},
	{
		"tm" : 1720857581481,
		"x" : 887,
		"y" : 484
	},
	{
		"tm" : 1720857581537,
		"x" : 808,
		"y" : 517
	}
]