[
	{
		"tm" : 1720966177345,
		"x" : 1318,
		"y" : 502
	},
	{
		"tm" : 1720966177400,
		"x" : 1172,
		"y" : 483
	},
	{
		"tm" : 1720966177802,
		"x" : 1170,
		"y" : 467
	},
	{
		"tm" : 1720966177864,
		"x" : 1095,
		"y" : 475
	},
	{
		"tm" : 1720966177915,
		"x" : 921,
		"y" : 475
	},
	{
		"tm" : 1720966177974,
		"x" : 742,
		"y" : 471
	},
	{
		"tm" : 1720966178026,
		"x" : 684,
		"y" : 463
	},
	{
		"tm" : 1720966178085,
		"x" : 626,
		"y" : 459
	},
	{
		"tm" : 1720966178147,
		"x" : 646,
		"y" : 438
	},
	{
		"tm" : 1720966178198,
		"x" : 742,
		"y" : 397
	},
	{
		"tm" : 1720966178256,
		"x" : 782,
		"y" : 401
	},
	{
		"tm" : 1720966178476,
		"x" : 765,
		"y" : 396
	},
	{
		"tm" : 1720966178574,
		"x" : 749,
		"y" : 398
	},
	{
		"tm" : 1720966178696,
		"x" : 733,
		"y" : 391
	},
	{
		"tm" : 1720966178757,
		"x" : 708,
		"y" : 387
	},
	{
		"tm" : 1720966178850,
		"x" : 691,
		"y" : 385
	},
	{
		"tm" : 1720966179352,
		"x" : 708,
		"y" : 384
	},
	{
		"tm" : 1720966179403,
		"x" : 769,
		"y" : 393
	},
	{
		"tm" : 1720966179460,
		"x" : 903,
		"y" : 439
	},
	{
		"tm" : 1720966179512,
		"x" : 1069,
		"y" : 497
	},
	{
		"tm" : 1720966179568,
		"x" : 1188,
		"y" : 544
	},
	{
		"tm" : 1720966179827,
		"x" : 1204,
		"y" : 553
	},
	{
		"tm" : 1720966179881,
		"x" : 1236,
		"y" : 545
	},
	{
		"tm" : 1720966179932,
		"x" : 1312,
		"y" : 545
	},
	{
		"tm" : 1720966179988,
		"x" : 1360,
		"y" : 541
	},
	{
		"tm" : 1720966180052,
		"x" : 1381,
		"y" : 541
	},
	{
		"tm" : 1720966180146,
		"x" : 1397,
		"y" : 541
	},
	{
		"tm" : 1720966180207,
		"x" : 1421,
		"y" : 538
	},
	{
		"tm" : 1720966180260,
		"x" : 1461,
		"y" : 536
	},
	{
		"tm" : 1720966180315,
		"x" : 1478,
		"y" : 536
	},
	{
		"tm" : 1720966180368,
		"x" : 1513,
		"y" : 537
	},
	{
		"tm" : 1720966180472,
		"x" : 1526,
		"y" : 550
	},
	{
		"tm" : 1720966180527,
		"x" : 1537,
		"y" : 577
	},
	{
		"tm" : 1720966180583,
		"x" : 1549,
		"y" : 617
	},
	{
		"tm" : 1720966180636,
		"x" : 1558,
		"y" : 646
	},
	{
		"tm" : 1720966180879,
		"x" : 1543,
		"y" : 654
	},
	{
		"tm" : 1720966180939,
		"x" : 1519,
		"y" : 654
	},
	{
		"tm" : 1720966181002,
		"x" : 1502,
		"y" : 652
	},
	{
		"tm" : 1720966181070,
		"x" : 1485,
		"y" : 648
	},
	{
		"tm" : 1720966181127,
		"x" : 1464,
		"y" : 644
	},
	{
		"tm" : 1720966181193,
		"x" : 1448,
		"y" : 642
	},
	{
		"tm" : 1720966181250,
		"x" : 1418,
		"y" : 636
	},
	{
		"tm" : 1720966181302,
		"x" : 1387,
		"y" : 629
	},
	{
		"tm" : 1720966181360,
		"x" : 1332,
		"y" : 608
	},
	{
		"tm" : 1720966181412,
		"x" : 1297,
		"y" : 597
	},
	{
		"tm" : 1720966181515,
		"x" : 1282,
		"y" : 587
	},
	{
		"tm" : 1720966181802,
		"x" : 1265,
		"y" : 582
	},
	{
		"tm" : 1720966181877,
		"x" : 1248,
		"y" : 580
	},
	{
		"tm" : 1720966181944,
		"x" : 1232,
		"y" : 575
	},
	{
		"tm" : 1720966182003,
		"x" : 1206,
		"y" : 570
	},
	{
		"tm" : 1720966182056,
		"x" : 1181,
		"y" : 570
	},
	{
		"tm" : 1720966182113,
		"x" : 1158,
		"y" : 570
	},
	{
		"tm" : 1720966182175,
		"x" : 1115,
		"y" : 572
	},
	{
		"tm" : 1720966182265,
		"x" : 1097,
		"y" : 567
	},
	{
		"tm" : 1720966182328,
		"x" : 1061,
		"y" : 561
	},
	{
		"tm" : 1720966182390,
		"x" : 1045,
		"y" : 557
	},
	{
		"tm" : 1720966182452,
		"x" : 1017,
		"y" : 553
	},
	{
		"tm" : 1720966182530,
		"x" : 997,
		"y" : 541
	},
	{
		"tm" : 1720966182592,
		"x" : 985,
		"y" : 525
	},
	{
		"tm" : 1720966182718,
		"x" : 968,
		"y" : 523
	},
	{
		"tm" : 1720966182811,
		"x" : 960,
		"y" : 538
	},
	{
		"tm" : 1720966182889,
		"x" : 945,
		"y" : 548
	},
	{
		"tm" : 1720966182941,
		"x" : 927,
		"y" : 559
	},
	{
		"tm" : 1720966183067,
		"x" : 918,
		"y" : 573
	},
	{
		"tm" : 1720966183512,
		"x" : 901,
		"y" : 582
	},
	{
		"tm" : 1720966184015,
		"x" : 881,
		"y" : 583
	},
	{
		"tm" : 1720966184072,
		"x" : 658,
		"y" : 487
	},
	{
		"tm" : 1720966184122,
		"x" : 405,
		"y" : 400
	},
	{
		"tm" : 1720966184181,
		"x" : 316,
		"y" : 384
	},
	{
		"tm" : 1720966184260,
		"x" : 299,
		"y" : 388
	},
	{
		"tm" : 1720966184375,
		"x" : 287,
		"y" : 377
	},
	{
		"tm" : 1720966184434,
		"x" : 273,
		"y" : 360
	},
	{
		"tm" : 1720966185200,
		"x" : 277,
		"y" : 344
	}
]