[
	{
		"tm" : 1720833151260,
		"x" : 1017,
		"y" : 239
	},
	{
		"tm" : 1720833151313,
		"x" : 1051,
		"y" : 243
	},
	{
		"tm" : 1720833151468,
		"x" : 1069,
		"y" : 242
	},
	{
		"tm" : 1720833151632,
		"x" : 1078,
		"y" : 228
	},
	{
		"tm" : 1720833151885,
		"x" : 1068,
		"y" : 248
	},
	{
		"tm" : 1720833151952,
		"x" : 979,
		"y" : 398
	},
	{
		"tm" : 1720833152004,
		"x" : 802,
		"y" : 615
	},
	{
		"tm" : 1720833152062,
		"x" : 631,
		"y" : 762
	},
	{
		"tm" : 1720833152116,
		"x" : 572,
		"y" : 799
	},
	{
		"tm" : 1720833152168,
		"x" : 552,
		"y" : 811
	},
	{
		"tm" : 1720833152220,
		"x" : 533,
		"y" : 825
	},
	{
		"tm" : 1720833152272,
		"x" : 506,
		"y" : 842
	},
	{
		"tm" : 1720833213188,
		"x" : 303,
		"y" : 854
	},
	{
		"tm" : 1720833213250,
		"x" : 389,
		"y" : 781
	},
	{
		"tm" : 1720833213308,
		"x" : 467,
		"y" : 694
	},
	{
		"tm" : 1720833213367,
		"x" : 500,
		"y" : 657
	},
	{
		"tm" : 1720833213420,
		"x" : 539,
		"y" : 621
	},
	{
		"tm" : 1720833213475,
		"x" : 569,
		"y" : 595
	},
	{
		"tm" : 1720833213534,
		"x" : 607,
		"y" : 554
	},
	{
		"tm" : 1720833213591,
		"x" : 624,
		"y" : 531
	},
	{
		"tm" : 1720833213675,
		"x" : 629,
		"y" : 514
	},
	{
		"tm" : 1720833213743,
		"x" : 635,
		"y" : 497
	},
	{
		"tm" : 1720833213895,
		"x" : 622,
		"y" : 514
	},
	{
		"tm" : 1720833213948,
		"x" : 568,
		"y" : 582
	},
	{
		"tm" : 1720833214005,
		"x" : 507,
		"y" : 668
	},
	{
		"tm" : 1720833214060,
		"x" : 498,
		"y" : 702
	},
	{
		"tm" : 1720833214113,
		"x" : 529,
		"y" : 682
	},
	{
		"tm" : 1720833214164,
		"x" : 590,
		"y" : 602
	},
	{
		"tm" : 1720833214216,
		"x" : 629,
		"y" : 552
	},
	{
		"tm" : 1720833214268,
		"x" : 640,
		"y" : 533
	},
	{
		"tm" : 1720833214324,
		"x" : 649,
		"y" : 514
	},
	{
		"tm" : 1720833214385,
		"x" : 670,
		"y" : 488
	},
	{
		"tm" : 1720833214436,
		"x" : 681,
		"y" : 470
	},
	{
		"tm" : 1720833214508,
		"x" : 692,
		"y" : 458
	},
	{
		"tm" : 1720833214572,
		"x" : 704,
		"y" : 446
	},
	{
		"tm" : 1720833214964,
		"x" : 717,
		"y" : 435
	},
	{
		"tm" : 1720833215022,
		"x" : 749,
		"y" : 428
	},
	{
		"tm" : 1720833215332,
		"x" : 765,
		"y" : 424
	},
	{
		"tm" : 1720833215716,
		"x" : 761,
		"y" : 444
	},
	{
		"tm" : 1720833215771,
		"x" : 717,
		"y" : 509
	},
	{
		"tm" : 1720833215831,
		"x" : 621,
		"y" : 619
	},
	{
		"tm" : 1720833215890,
		"x" : 511,
		"y" : 737
	},
	{
		"tm" : 1720833215953,
		"x" : 444,
		"y" : 804
	},
	{
		"tm" : 1720833216004,
		"x" : 421,
		"y" : 833
	},
	{
		"tm" : 1720833216077,
		"x" : 412,
		"y" : 848
	}
]