[
	{
		"tm" : 1720879413945,
		"x" : 761,
		"y" : 640
	},
	{
		"tm" : 1720879413998,
		"x" : 864,
		"y" : 638
	},
	{
		"tm" : 1720879414052,
		"x" : 1091,
		"y" : 490
	},
	{
		"tm" : 1720879414108,
		"x" : 1120,
		"y" : 437
	},
	{
		"tm" : 1720879414242,
		"x" : 1106,
		"y" : 445
	},
	{
		"tm" : 1720879414295,
		"x" : 1038,
		"y" : 505
	},
	{
		"tm" : 1720879414348,
		"x" : 932,
		"y" : 580
	},
	{
		"tm" : 1720879414428,
		"x" : 921,
		"y" : 593
	},
	{
		"tm" : 1720879414496,
		"x" : 918,
		"y" : 609
	},
	{
		"tm" : 1720879414668,
		"x" : 919,
		"y" : 625
	},
	{
		"tm" : 1720879415315,
		"x" : 937,
		"y" : 631
	},
	{
		"tm" : 1720879415378,
		"x" : 1078,
		"y" : 628
	},
	{
		"tm" : 1720879415434,
		"x" : 1374,
		"y" : 615
	},
	{
		"tm" : 1720879415490,
		"x" : 1659,
		"y" : 544
	},
	{
		"tm" : 1720879415554,
		"x" : 1751,
		"y" : 517
	},
	{
		"tm" : 1720879415729,
		"x" : 1770,
		"y" : 525
	},
	{
		"tm" : 1720879415782,
		"x" : 1800,
		"y" : 525
	},
	{
		"tm" : 1720879415874,
		"x" : 1744,
		"y" : 553
	},
	{
		"tm" : 1720879416071,
		"x" : 40,
		"y" : 1038
	},
	{
		"tm" : 1720879416165,
		"x" : 57,
		"y" : 1020
	},
	{
		"tm" : 1720879416234,
		"x" : 75,
		"y" : 1029
	},
	{
		"tm" : 1720879422707,
		"x" : 185,
		"y" : 1023
	},
	{
		"tm" : 1720879422758,
		"x" : 205,
		"y" : 855
	},
	{
		"tm" : 1720879422814,
		"x" : 205,
		"y" : 756
	},
	{
		"tm" : 1720879423252,
		"x" : 192,
		"y" : 767
	},
	{
		"tm" : 1720879424228,
		"x" : 221,
		"y" : 777
	},
	{
		"tm" : 1720879424280,
		"x" : 283,
		"y" : 780
	},
	{
		"tm" : 1720879425145,
		"x" : 288,
		"y" : 798
	},
	{
		"tm" : 1720879425198,
		"x" : 303,
		"y" : 822
	},
	{
		"tm" : 1720879425331,
		"x" : 320,
		"y" : 826
	},
	{
		"tm" : 1720879425393,
		"x" : 342,
		"y" : 819
	},
	{
		"tm" : 1720879425454,
		"x" : 418,
		"y" : 791
	},
	{
		"tm" : 1720879425518,
		"x" : 462,
		"y" : 748
	},
	{
		"tm" : 1720879425574,
		"x" : 501,
		"y" : 692
	},
	{
		"tm" : 1720879425628,
		"x" : 507,
		"y" : 665
	},
	{
		"tm" : 1720879425690,
		"x" : 505,
		"y" : 644
	},
	{
		"tm" : 1720879429349,
		"x" : 500,
		"y" : 628
	},
	{
		"tm" : 1720879429412,
		"x" : 488,
		"y" : 616
	},
	{
		"tm" : 1720879429469,
		"x" : 469,
		"y" : 605
	},
	{
		"tm" : 1720879429525,
		"x" : 443,
		"y" : 601
	},
	{
		"tm" : 1720879429576,
		"x" : 405,
		"y" : 605
	},
	{
		"tm" : 1720879429631,
		"x" : 365,
		"y" : 624
	},
	{
		"tm" : 1720879429687,
		"x" : 324,
		"y" : 660
	},
	{
		"tm" : 1720879429974,
		"x" : 315,
		"y" : 675
	},
	{
		"tm" : 1720879430244,
		"x" : 301,
		"y" : 686
	},
	{
		"tm" : 1720879430304,
		"x" : 285,
		"y" : 709
	},
	{
		"tm" : 1720879430502,
		"x" : 301,
		"y" : 704
	},
	{
		"tm" : 1720879430553,
		"x" : 417,
		"y" : 601
	},
	{
		"tm" : 1720879430604,
		"x" : 703,
		"y" : 478
	},
	{
		"tm" : 1720879430666,
		"x" : 1172,
		"y" : 398
	},
	{
		"tm" : 1720879430787,
		"x" : 1249,
		"y" : 388
	},
	{
		"tm" : 1720879430874,
		"x" : 1234,
		"y" : 379
	},
	{
		"tm" : 1720879430927,
		"x" : 1202,
		"y" : 374
	},
	{
		"tm" : 1720879430980,
		"x" : 1165,
		"y" : 372
	},
	{
		"tm" : 1720879431031,
		"x" : 1107,
		"y" : 368
	},
	{
		"tm" : 1720879431085,
		"x" : 1019,
		"y" : 362
	},
	{
		"tm" : 1720879431149,
		"x" : 946,
		"y" : 353
	},
	{
		"tm" : 1720879431232,
		"x" : 939,
		"y" : 369
	},
	{
		"tm" : 1720879431287,
		"x" : 931,
		"y" : 527
	},
	{
		"tm" : 1720879431342,
		"x" : 918,
		"y" : 606
	},
	{
		"tm" : 1720879431509,
		"x" : 928,
		"y" : 590
	},
	{
		"tm" : 1720879431560,
		"x" : 958,
		"y" : 550
	},
	{
		"tm" : 1720879431612,
		"x" : 1013,
		"y" : 509
	},
	{
		"tm" : 1720879431699,
		"x" : 1020,
		"y" : 492
	},
	{
		"tm" : 1720879431751,
		"x" : 999,
		"y" : 465
	},
	{
		"tm" : 1720879431812,
		"x" : 966,
		"y" : 422
	},
	{
		"tm" : 1720879431866,
		"x" : 924,
		"y" : 382
	},
	{
		"tm" : 1720879431928,
		"x" : 908,
		"y" : 369
	},
	{
		"tm" : 1720879431996,
		"x" : 892,
		"y" : 362
	},
	{
		"tm" : 1720879432054,
		"x" : 843,
		"y" : 350
	},
	{
		"tm" : 1720879432113,
		"x" : 777,
		"y" : 318
	},
	{
		"tm" : 1720879432166,
		"x" : 758,
		"y" : 299
	},
	{
		"tm" : 1720879432411,
		"x" : 746,
		"y" : 322
	},
	{
		"tm" : 1720879432465,
		"x" : 732,
		"y" : 351
	},
	{
		"tm" : 1720879432796,
		"x" : 718,
		"y" : 363
	},
	{
		"tm" : 1720879432847,
		"x" : 673,
		"y" : 388
	},
	{
		"tm" : 1720879432900,
		"x" : 602,
		"y" : 441
	},
	{
		"tm" : 1720879432955,
		"x" : 551,
		"y" : 469
	},
	{
		"tm" : 1720879433135,
		"x" : 535,
		"y" : 466
	},
	{
		"tm" : 1720879433625,
		"x" : 537,
		"y" : 449
	},
	{
		"tm" : 1720879433875,
		"x" : 551,
		"y" : 439
	},
	{
		"tm" : 1720879435398,
		"x" : 568,
		"y" : 422
	},
	{
		"tm" : 1720879435453,
		"x" : 622,
		"y" : 362
	},
	{
		"tm" : 1720879435545,
		"x" : 640,
		"y" : 348
	},
	{
		"tm" : 1720879435601,
		"x" : 672,
		"y" : 348
	},
	{
		"tm" : 1720879435656,
		"x" : 713,
		"y" : 348
	},
	{
		"tm" : 1720879435715,
		"x" : 736,
		"y" : 381
	},
	{
		"tm" : 1720879435771,
		"x" : 729,
		"y" : 425
	},
	{
		"tm" : 1720879435832,
		"x" : 709,
		"y" : 445
	},
	{
		"tm" : 1720879436029,
		"x" : 693,
		"y" : 447
	},
	{
		"tm" : 1720879436091,
		"x" : 693,
		"y" : 427
	},
	{
		"tm" : 1720879436160,
		"x" : 694,
		"y" : 411
	},
	{
		"tm" : 1720879436213,
		"x" : 711,
		"y" : 356
	},
	{
		"tm" : 1720879436269,
		"x" : 717,
		"y" : 333
	},
	{
		"tm" : 1720879437186,
		"x" : 702,
		"y" : 339
	},
	{
		"tm" : 1720879437245,
		"x" : 686,
		"y" : 368
	},
	{
		"tm" : 1720879437309,
		"x" : 678,
		"y" : 383
	},
	{
		"tm" : 1720879437432,
		"x" : 673,
		"y" : 401
	},
	{
		"tm" : 1720879437805,
		"x" : 675,
		"y" : 418
	},
	{
		"tm" : 1720879438278,
		"x" : 689,
		"y" : 432
	},
	{
		"tm" : 1720879438331,
		"x" : 883,
		"y" : 445
	},
	{
		"tm" : 1720879438382,
		"x" : 1112,
		"y" : 414
	},
	{
		"tm" : 1720879438446,
		"x" : 1153,
		"y" : 391
	},
	{
		"tm" : 1720879438508,
		"x" : 1111,
		"y" : 360
	},
	{
		"tm" : 1720879438766,
		"x" : 1099,
		"y" : 349
	},
	{
		"tm" : 1720879439049,
		"x" : 1093,
		"y" : 334
	},
	{
		"tm" : 1720879439995,
		"x" : 1115,
		"y" : 340
	},
	{
		"tm" : 1720879440052,
		"x" : 1229,
		"y" : 451
	},
	{
		"tm" : 1720879440109,
		"x" : 1359,
		"y" : 607
	},
	{
		"tm" : 1720879440245,
		"x" : 1368,
		"y" : 579
	},
	{
		"tm" : 1720879440305,
		"x" : 1369,
		"y" : 544
	},
	{
		"tm" : 1720879440374,
		"x" : 1371,
		"y" : 525
	},
	{
		"tm" : 1720879440431,
		"x" : 1359,
		"y" : 495
	},
	{
		"tm" : 1720879440833,
		"x" : 1373,
		"y" : 487
	},
	{
		"tm" : 1720879441037,
		"x" : 1395,
		"y" : 478
	},
	{
		"tm" : 1720879441088,
		"x" : 1438,
		"y" : 417
	},
	{
		"tm" : 1720879441145,
		"x" : 1457,
		"y" : 364
	},
	{
		"tm" : 1720879441196,
		"x" : 1462,
		"y" : 335
	},
	{
		"tm" : 1720879441414,
		"x" : 1475,
		"y" : 320
	},
	{
		"tm" : 1720879441474,
		"x" : 1483,
		"y" : 303
	},
	{
		"tm" : 1720879441695,
		"x" : 1493,
		"y" : 290
	},
	{
		"tm" : 1720879441881,
		"x" : 1475,
		"y" : 284
	},
	{
		"tm" : 1720879441933,
		"x" : 1408,
		"y" : 267
	},
	{
		"tm" : 1720879441988,
		"x" : 1375,
		"y" : 254
	},
	{
		"tm" : 1720879442298,
		"x" : 1360,
		"y" : 248
	},
	{
		"tm" : 1720879442677,
		"x" : 1343,
		"y" : 245
	},
	{
		"tm" : 1720879442728,
		"x" : 1309,
		"y" : 258
	},
	{
		"tm" : 1720879442782,
		"x" : 1163,
		"y" : 273
	},
	{
		"tm" : 1720879442837,
		"x" : 1058,
		"y" : 282
	},
	{
		"tm" : 1720879442894,
		"x" : 1023,
		"y" : 287
	},
	{
		"tm" : 1720879443079,
		"x" : 1023,
		"y" : 305
	},
	{
		"tm" : 1720879443143,
		"x" : 1033,
		"y" : 318
	},
	{
		"tm" : 1720879444035,
		"x" : 1062,
		"y" : 341
	},
	{
		"tm" : 1720879444089,
		"x" : 1127,
		"y" : 372
	},
	{
		"tm" : 1720879444153,
		"x" : 1220,
		"y" : 399
	},
	{
		"tm" : 1720879444236,
		"x" : 1221,
		"y" : 423
	},
	{
		"tm" : 1720879444298,
		"x" : 1143,
		"y" : 493
	},
	{
		"tm" : 1720879444360,
		"x" : 1043,
		"y" : 566
	},
	{
		"tm" : 1720879444422,
		"x" : 1005,
		"y" : 597
	},
	{
		"tm" : 1720879444479,
		"x" : 993,
		"y" : 609
	},
	{
		"tm" : 1720879444532,
		"x" : 983,
		"y" : 627
	},
	{
		"tm" : 1720879445564,
		"x" : 965,
		"y" : 629
	},
	{
		"tm" : 1720879445628,
		"x" : 852,
		"y" : 596
	},
	{
		"tm" : 1720879445683,
		"x" : 765,
		"y" : 589
	},
	{
		"tm" : 1720879445741,
		"x" : 741,
		"y" : 592
	},
	{
		"tm" : 1720879445796,
		"x" : 670,
		"y" : 608
	},
	{
		"tm" : 1720879445859,
		"x" : 587,
		"y" : 646
	},
	{
		"tm" : 1720879445912,
		"x" : 485,
		"y" : 703
	},
	{
		"tm" : 1720879445968,
		"x" : 439,
		"y" : 724
	},
	{
		"tm" : 1720879448875,
		"x" : 436,
		"y" : 704
	},
	{
		"tm" : 1720879448933,
		"x" : 577,
		"y" : 447
	},
	{
		"tm" : 1720879448989,
		"x" : 664,
		"y" : 275
	},
	{
		"tm" : 1720879449236,
		"x" : 637,
		"y" : 288
	},
	{
		"tm" : 1720879449296,
		"x" : 586,
		"y" : 329
	},
	{
		"tm" : 1720879449783,
		"x" : 570,
		"y" : 332
	},
	{
		"tm" : 1720879450593,
		"x" : 554,
		"y" : 343
	},
	{
		"tm" : 1720879450654,
		"x" : 470,
		"y" : 445
	},
	{
		"tm" : 1720879450712,
		"x" : 317,
		"y" : 619
	},
	{
		"tm" : 1720879450780,
		"x" : 234,
		"y" : 676
	},
	{
		"tm" : 1720879453479,
		"x" : 220,
		"y" : 686
	},
	{
		"tm" : 1720879453961,
		"x" : 207,
		"y" : 701
	},
	{
		"tm" : 1720879454017,
		"x" : 195,
		"y" : 753
	},
	{
		"tm" : 1720879454073,
		"x" : 193,
		"y" : 774
	},
	{
		"tm" : 1720879454124,
		"x" : 207,
		"y" : 782
	},
	{
		"tm" : 1720879454261,
		"x" : 212,
		"y" : 799
	},
	{
		"tm" : 1720879454474,
		"x" : 229,
		"y" : 802
	},
	{
		"tm" : 1720879454525,
		"x" : 268,
		"y" : 844
	},
	{
		"tm" : 1720879454582,
		"x" : 343,
		"y" : 897
	},
	{
		"tm" : 1720879454641,
		"x" : 460,
		"y" : 912
	},
	{
		"tm" : 1720879454697,
		"x" : 630,
		"y" : 849
	},
	{
		"tm" : 1720879454752,
		"x" : 720,
		"y" : 745
	},
	{
		"tm" : 1720879454807,
		"x" : 756,
		"y" : 657
	},
	{
		"tm" : 1720879454865,
		"x" : 777,
		"y" : 618
	},
	{
		"tm" : 1720879454917,
		"x" : 784,
		"y" : 598
	},
	{
		"tm" : 1720879454972,
		"x" : 794,
		"y" : 533
	},
	{
		"tm" : 1720879455027,
		"x" : 796,
		"y" : 463
	},
	{
		"tm" : 1720879455080,
		"x" : 791,
		"y" : 433
	},
	{
		"tm" : 1720879455133,
		"x" : 789,
		"y" : 417
	},
	{
		"tm" : 1720879455205,
		"x" : 793,
		"y" : 401
	},
	{
		"tm" : 1720879455566,
		"x" : 804,
		"y" : 389
	},
	{
		"tm" : 1720879455768,
		"x" : 810,
		"y" : 374
	},
	{
		"tm" : 1720879455883,
		"x" : 813,
		"y" : 357
	},
	{
		"tm" : 1720879456790,
		"x" : 797,
		"y" : 372
	},
	{
		"tm" : 1720879456845,
		"x" : 546,
		"y" : 562
	},
	{
		"tm" : 1720879456899,
		"x" : 353,
		"y" : 663
	},
	{
		"tm" : 1720879456954,
		"x" : 258,
		"y" : 683
	},
	{
		"tm" : 1720879457025,
		"x" : 176,
		"y" : 695
	},
	{
		"tm" : 1720879457091,
		"x" : 146,
		"y" : 730
	},
	{
		"tm" : 1720879457585,
		"x" : 162,
		"y" : 723
	},
	{
		"tm" : 1720879457636,
		"x" : 246,
		"y" : 720
	},
	{
		"tm" : 1720879457687,
		"x" : 438,
		"y" : 726
	},
	{
		"tm" : 1720879457741,
		"x" : 803,
		"y" : 702
	},
	{
		"tm" : 1720879457803,
		"x" : 935,
		"y" : 651
	},
	{
		"tm" : 1720879457858,
		"x" : 972,
		"y" : 619
	},
	{
		"tm" : 1720879458020,
		"x" : 959,
		"y" : 605
	},
	{
		"tm" : 1720879458075,
		"x" : 940,
		"y" : 595
	},
	{
		"tm" : 1720879458130,
		"x" : 893,
		"y" : 556
	},
	{
		"tm" : 1720879458183,
		"x" : 823,
		"y" : 502
	},
	{
		"tm" : 1720879458239,
		"x" : 804,
		"y" : 482
	},
	{
		"tm" : 1720879458453,
		"x" : 769,
		"y" : 543
	},
	{
		"tm" : 1720879458504,
		"x" : 564,
		"y" : 1017
	},
	{
		"tm" : 1720879473629,
		"x" : 244,
		"y" : 1039
	},
	{
		"tm" : 1720879473689,
		"x" : 671,
		"y" : 818
	},
	{
		"tm" : 1720879473749,
		"x" : 989,
		"y" : 654
	},
	{
		"tm" : 1720879473801,
		"x" : 1014,
		"y" : 627
	},
	{
		"tm" : 1720879473857,
		"x" : 1007,
		"y" : 606
	},
	{
		"tm" : 1720879473980,
		"x" : 1002,
		"y" : 590
	},
	{
		"tm" : 1720879474036,
		"x" : 1013,
		"y" : 557
	},
	{
		"tm" : 1720879474092,
		"x" : 1037,
		"y" : 497
	},
	{
		"tm" : 1720879474154,
		"x" : 1051,
		"y" : 461
	},
	{
		"tm" : 1720879475350,
		"x" : 1040,
		"y" : 475
	},
	{
		"tm" : 1720879475412,
		"x" : 1028,
		"y" : 488
	},
	{
		"tm" : 1720879475482,
		"x" : 998,
		"y" : 506
	},
	{
		"tm" : 1720879475545,
		"x" : 939,
		"y" : 540
	},
	{
		"tm" : 1720879475742,
		"x" : 932,
		"y" : 556
	},
	{
		"tm" : 1720879475795,
		"x" : 947,
		"y" : 585
	},
	{
		"tm" : 1720879475850,
		"x" : 957,
		"y" : 603
	},
	{
		"tm" : 1720879475904,
		"x" : 939,
		"y" : 629
	},
	{
		"tm" : 1720879475977,
		"x" : 924,
		"y" : 637
	},
	{
		"tm" : 1720879476247,
		"x" : 903,
		"y" : 634
	},
	{
		"tm" : 1720879478987,
		"x" : 911,
		"y" : 614
	},
	{
		"tm" : 1720879479041,
		"x" : 992,
		"y" : 583
	},
	{
		"tm" : 1720879479094,
		"x" : 1043,
		"y" : 564
	},
	{
		"tm" : 1720879479149,
		"x" : 1060,
		"y" : 551
	},
	{
		"tm" : 1720879479201,
		"x" : 1078,
		"y" : 536
	},
	{
		"tm" : 1720879479254,
		"x" : 1100,
		"y" : 495
	},
	{
		"tm" : 1720879479315,
		"x" : 1121,
		"y" : 442
	},
	{
		"tm" : 1720879479374,
		"x" : 1118,
		"y" : 418
	},
	{
		"tm" : 1720879479468,
		"x" : 1099,
		"y" : 411
	},
	{
		"tm" : 1720879479520,
		"x" : 1075,
		"y" : 422
	},
	{
		"tm" : 1720879479577,
		"x" : 1034,
		"y" : 446
	},
	{
		"tm" : 1720879479629,
		"x" : 755,
		"y" : 545
	},
	{
		"tm" : 1720879479683,
		"x" : 173,
		"y" : 708
	},
	{
		"tm" : 1720879479740,
		"x" : 0,
		"y" : 799
	},
	{
		"tm" : 1720879480125,
		"x" : 13,
		"y" : 813
	},
	{
		"tm" : 1720879480188,
		"x" : 205,
		"y" : 824
	},
	{
		"tm" : 1720879480250,
		"x" : 688,
		"y" : 823
	},
	{
		"tm" : 1720879480302,
		"x" : 1011,
		"y" : 704
	},
	{
		"tm" : 1720879480358,
		"x" : 1038,
		"y" : 643
	},
	{
		"tm" : 1720879480414,
		"x" : 1039,
		"y" : 580
	},
	{
		"tm" : 1720879480468,
		"x" : 1040,
		"y" : 549
	},
	{
		"tm" : 1720879480550,
		"x" : 1055,
		"y" : 538
	},
	{
		"tm" : 1720879480609,
		"x" : 1091,
		"y" : 501
	},
	{
		"tm" : 1720879480669,
		"x" : 1129,
		"y" : 445
	},
	{
		"tm" : 1720879480731,
		"x" : 1142,
		"y" : 424
	},
	{
		"tm" : 1720879480787,
		"x" : 1150,
		"y" : 409
	},
	{
		"tm" : 1720879480850,
		"x" : 1154,
		"y" : 393
	},
	{
		"tm" : 1720879481133,
		"x" : 1145,
		"y" : 414
	},
	{
		"tm" : 1720879481188,
		"x" : 956,
		"y" : 680
	},
	{
		"tm" : 1720879481366,
		"x" : 326,
		"y" : 1039
	},
	{
		"tm" : 1720879503393,
		"x" : 204,
		"y" : 1038
	},
	{
		"tm" : 1720879503449,
		"x" : 394,
		"y" : 889
	},
	{
		"tm" : 1720879503503,
		"x" : 639,
		"y" : 681
	},
	{
		"tm" : 1720879503558,
		"x" : 752,
		"y" : 584
	},
	{
		"tm" : 1720879503612,
		"x" : 819,
		"y" : 509
	},
	{
		"tm" : 1720879503675,
		"x" : 968,
		"y" : 440
	},
	{
		"tm" : 1720879503739,
		"x" : 1152,
		"y" : 407
	},
	{
		"tm" : 1720879503792,
		"x" : 1420,
		"y" : 377
	},
	{
		"tm" : 1720879503847,
		"x" : 1591,
		"y" : 310
	},
	{
		"tm" : 1720879503900,
		"x" : 1644,
		"y" : 261
	},
	{
		"tm" : 1720879503955,
		"x" : 1653,
		"y" : 243
	},
	{
		"tm" : 1720879504009,
		"x" : 1617,
		"y" : 243
	},
	{
		"tm" : 1720879504063,
		"x" : 1386,
		"y" : 425
	},
	{
		"tm" : 1720879504124,
		"x" : 829,
		"y" : 763
	},
	{
		"tm" : 1720879513078,
		"x" : 211,
		"y" : 1031
	},
	{
		"tm" : 1720879513142,
		"x" : 495,
		"y" : 711
	},
	{
		"tm" : 1720879513196,
		"x" : 529,
		"y" : 617
	},
	{
		"tm" : 1720879513478,
		"x" : 516,
		"y" : 635
	},
	{
		"tm" : 1720879513538,
		"x" : 507,
		"y" : 668
	},
	{
		"tm" : 1720879513593,
		"x" : 514,
		"y" : 689
	},
	{
		"tm" : 1720879513649,
		"x" : 585,
		"y" : 704
	},
	{
		"tm" : 1720879513702,
		"x" : 682,
		"y" : 696
	},
	{
		"tm" : 1720879513794,
		"x" : 697,
		"y" : 689
	},
	{
		"tm" : 1720879513857,
		"x" : 723,
		"y" : 666
	},
	{
		"tm" : 1720879513963,
		"x" : 717,
		"y" : 648
	},
	{
		"tm" : 1720879514026,
		"x" : 675,
		"y" : 637
	},
	{
		"tm" : 1720879514080,
		"x" : 600,
		"y" : 641
	},
	{
		"tm" : 1720879514134,
		"x" : 547,
		"y" : 649
	},
	{
		"tm" : 1720879514680,
		"x" : 579,
		"y" : 649
	},
	{
		"tm" : 1720879514742,
		"x" : 702,
		"y" : 649
	},
	{
		"tm" : 1720879514797,
		"x" : 770,
		"y" : 667
	},
	{
		"tm" : 1720879514851,
		"x" : 823,
		"y" : 653
	},
	{
		"tm" : 1720879515022,
		"x" : 837,
		"y" : 638
	},
	{
		"tm" : 1720879515085,
		"x" : 814,
		"y" : 638
	},
	{
		"tm" : 1720879515146,
		"x" : 775,
		"y" : 636
	},
	{
		"tm" : 1720879515883,
		"x" : 767,
		"y" : 652
	},
	{
		"tm" : 1720879515935,
		"x" : 773,
		"y" : 690
	},
	{
		"tm" : 1720879515997,
		"x" : 818,
		"y" : 809
	},
	{
		"tm" : 1720879516052,
		"x" : 873,
		"y" : 953
	},
	{
		"tm" : 1720879516104,
		"x" : 877,
		"y" : 976
	},
	{
		"tm" : 1720879516196,
		"x" : 891,
		"y" : 984
	},
	{
		"tm" : 1720879516250,
		"x" : 909,
		"y" : 985
	},
	{
		"tm" : 1720879516305,
		"x" : 930,
		"y" : 989
	},
	{
		"tm" : 1720879516381,
		"x" : 947,
		"y" : 993
	},
	{
		"tm" : 1720879516452,
		"x" : 966,
		"y" : 984
	},
	{
		"tm" : 1720879516516,
		"x" : 993,
		"y" : 975
	},
	{
		"tm" : 1720879516633,
		"x" : 1008,
		"y" : 968
	},
	{
		"tm" : 1720879517111,
		"x" : 1000,
		"y" : 945
	},
	{
		"tm" : 1720879517175,
		"x" : 794,
		"y" : 688
	},
	{
		"tm" : 1720879517237,
		"x" : 470,
		"y" : 431
	},
	{
		"tm" : 1720879517295,
		"x" : 448,
		"y" : 401
	},
	{
		"tm" : 1720879517347,
		"x" : 464,
		"y" : 374
	},
	{
		"tm" : 1720879517402,
		"x" : 501,
		"y" : 353
	},
	{
		"tm" : 1720879517454,
		"x" : 554,
		"y" : 335
	},
	{
		"tm" : 1720879517511,
		"x" : 625,
		"y" : 286
	},
	{
		"tm" : 1720879517563,
		"x" : 642,
		"y" : 271
	},
	{
		"tm" : 1720879517681,
		"x" : 661,
		"y" : 267
	},
	{
		"tm" : 1720879517735,
		"x" : 697,
		"y" : 266
	},
	{
		"tm" : 1720879517790,
		"x" : 756,
		"y" : 308
	},
	{
		"tm" : 1720879517844,
		"x" : 778,
		"y" : 325
	},
	{
		"tm" : 1720879517903,
		"x" : 801,
		"y" : 350
	},
	{
		"tm" : 1720879517985,
		"x" : 804,
		"y" : 367
	},
	{
		"tm" : 1720879518046,
		"x" : 809,
		"y" : 398
	},
	{
		"tm" : 1720879518108,
		"x" : 829,
		"y" : 439
	},
	{
		"tm" : 1720879518165,
		"x" : 866,
		"y" : 445
	},
	{
		"tm" : 1720879518243,
		"x" : 856,
		"y" : 431
	},
	{
		"tm" : 1720879518295,
		"x" : 839,
		"y" : 422
	},
	{
		"tm" : 1720879518489,
		"x" : 836,
		"y" : 458
	},
	{
		"tm" : 1720879518664,
		"x" : 321,
		"y" : 1032
	},
	{
		"tm" : 1720879528631,
		"x" : 189,
		"y" : 1037
	},
	{
		"tm" : 1720879528687,
		"x" : 253,
		"y" : 954
	},
	{
		"tm" : 1720879528741,
		"x" : 361,
		"y" : 790
	},
	{
		"tm" : 1720879528795,
		"x" : 467,
		"y" : 585
	},
	{
		"tm" : 1720879528849,
		"x" : 475,
		"y" : 530
	},
	{
		"tm" : 1720879528907,
		"x" : 446,
		"y" : 488
	},
	{
		"tm" : 1720879530740,
		"x" : 429,
		"y" : 493
	},
	{
		"tm" : 1720879530804,
		"x" : 381,
		"y" : 526
	},
	{
		"tm" : 1720879530877,
		"x" : 348,
		"y" : 546
	},
	{
		"tm" : 1720879530999,
		"x" : 334,
		"y" : 556
	},
	{
		"tm" : 1720879531061,
		"x" : 327,
		"y" : 575
	},
	{
		"tm" : 1720879531115,
		"x" : 374,
		"y" : 777
	},
	{
		"tm" : 1720879531169,
		"x" : 509,
		"y" : 881
	},
	{
		"tm" : 1720879531222,
		"x" : 730,
		"y" : 910
	},
	{
		"tm" : 1720879531277,
		"x" : 848,
		"y" : 876
	},
	{
		"tm" : 1720879531338,
		"x" : 878,
		"y" : 810
	},
	{
		"tm" : 1720879531392,
		"x" : 859,
		"y" : 726
	},
	{
		"tm" : 1720879531448,
		"x" : 823,
		"y" : 656
	},
	{
		"tm" : 1720879531500,
		"x" : 788,
		"y" : 590
	},
	{
		"tm" : 1720879531563,
		"x" : 773,
		"y" : 547
	},
	{
		"tm" : 1720879531620,
		"x" : 759,
		"y" : 521
	},
	{
		"tm" : 1720879532553,
		"x" : 781,
		"y" : 557
	},
	{
		"tm" : 1720879532609,
		"x" : 912,
		"y" : 716
	},
	{
		"tm" : 1720879532661,
		"x" : 950,
		"y" : 735
	},
	{
		"tm" : 1720879532719,
		"x" : 1003,
		"y" : 729
	},
	{
		"tm" : 1720879532781,
		"x" : 1289,
		"y" : 649
	},
	{
		"tm" : 1720879532831,
		"x" : 1474,
		"y" : 594
	},
	{
		"tm" : 1720879532894,
		"x" : 1534,
		"y" : 537
	},
	{
		"tm" : 1720879532951,
		"x" : 1536,
		"y" : 514
	},
	{
		"tm" : 1720879533013,
		"x" : 1541,
		"y" : 489
	},
	{
		"tm" : 1720879533073,
		"x" : 1549,
		"y" : 474
	},
	{
		"tm" : 1720879533325,
		"x" : 1560,
		"y" : 462
	},
	{
		"tm" : 1720879533488,
		"x" : 1573,
		"y" : 450
	},
	{
		"tm" : 1720879533850,
		"x" : 1550,
		"y" : 447
	},
	{
		"tm" : 1720879533904,
		"x" : 1510,
		"y" : 456
	}
]