[
	{
		"tm" : 1720912877804,
		"x" : 649,
		"y" : 1020
	},
	{
		"tm" : 1720912877861,
		"x" : 649,
		"y" : 778
	},
	{
		"tm" : 1720912877918,
		"x" : 699,
		"y" : 440
	},
	{
		"tm" : 1720912877972,
		"x" : 736,
		"y" : 274
	},
	{
		"tm" : 1720912878028,
		"x" : 749,
		"y" : 234
	},
	{
		"tm" : 1720912878084,
		"x" : 808,
		"y" : 247
	},
	{
		"tm" : 1720912878268,
		"x" : 797,
		"y" : 234
	},
	{
		"tm" : 1720912878324,
		"x" : 704,
		"y" : 219
	},
	{
		"tm" : 1720912878383,
		"x" : 659,
		"y" : 205
	},
	{
		"tm" : 1720912878437,
		"x" : 629,
		"y" : 195
	},
	{
		"tm" : 1720912878492,
		"x" : 596,
		"y" : 182
	},
	{
		"tm" : 1720912878549,
		"x" : 572,
		"y" : 166
	},
	{
		"tm" : 1720912878608,
		"x" : 556,
		"y" : 155
	},
	{
		"tm" : 1720912878988,
		"x" : 540,
		"y" : 157
	},
	{
		"tm" : 1720912879044,
		"x" : 470,
		"y" : 166
	},
	{
		"tm" : 1720912879113,
		"x" : 336,
		"y" : 180
	},
	{
		"tm" : 1720912879164,
		"x" : 225,
		"y" : 180
	},
	{
		"tm" : 1720912879222,
		"x" : 153,
		"y" : 180
	},
	{
		"tm" : 1720912879276,
		"x" : 117,
		"y" : 180
	},
	{
		"tm" : 1720912879477,
		"x" : 101,
		"y" : 178
	},
	{
		"tm" : 1720912879582,
		"x" : 85,
		"y" : 175
	},
	{
		"tm" : 1720912879636,
		"x" : 63,
		"y" : 175
	},
	{
		"tm" : 1720912880716,
		"x" : 89,
		"y" : 187
	},
	{
		"tm" : 1720912880772,
		"x" : 335,
		"y" : 317
	},
	{
		"tm" : 1720912880829,
		"x" : 629,
		"y" : 433
	},
	{
		"tm" : 1720912880884,
		"x" : 746,
		"y" : 449
	},
	{
		"tm" : 1720912880996,
		"x" : 733,
		"y" : 434
	},
	{
		"tm" : 1720912881052,
		"x" : 709,
		"y" : 418
	},
	{
		"tm" : 1720912881164,
		"x" : 685,
		"y" : 407
	},
	{
		"tm" : 1720912881278,
		"x" : 671,
		"y" : 397
	},
	{
		"tm" : 1720912881788,
		"x" : 656,
		"y" : 415
	},
	{
		"tm" : 1720912881844,
		"x" : 648,
		"y" : 710
	},
	{
		"tm" : 1720912907644,
		"x" : 796,
		"y" : 1037
	},
	{
		"tm" : 1720912907702,
		"x" : 951,
		"y" : 1018
	},
	{
		"tm" : 1720912907756,
		"x" : 1013,
		"y" : 1000
	},
	{
		"tm" : 1720912907807,
		"x" : 1027,
		"y" : 988
	},
	{
		"tm" : 1720912907860,
		"x" : 1043,
		"y" : 973
	},
	{
		"tm" : 1720912907980,
		"x" : 1055,
		"y" : 962
	},
	{
		"tm" : 1720912908156,
		"x" : 1072,
		"y" : 959
	},
	{
		"tm" : 1720912908629,
		"x" : 1055,
		"y" : 967
	},
	{
		"tm" : 1720912908685,
		"x" : 892,
		"y" : 987
	},
	{
		"tm" : 1720912908740,
		"x" : 753,
		"y" : 1007
	},
	{
		"tm" : 1720912908800,
		"x" : 662,
		"y" : 1020
	},
	{
		"tm" : 1720912908853,
		"x" : 637,
		"y" : 1027
	}
]