[
	{
		"tm" : 1720831794738,
		"x" : 31,
		"y" : 719
	},
	{
		"tm" : 1720831795135,
		"x" : 28,
		"y" : 722
	},
	{
		"tm" : 1720831795545,
		"x" : 28,
		"y" : 725
	},
	{
		"tm" : 1720831795955,
		"x" : 28,
		"y" : 728
	},
	{
		"tm" : 1720831796376,
		"x" : 25,
		"y" : 731
	},
	{
		"tm" : 1720831796780,
		"x" : 25,
		"y" : 734
	},
	{
		"tm" : 1720831797182,
		"x" : 25,
		"y" : 737
	},
	{
		"tm" : 1720831797578,
		"x" : 25,
		"y" : 740
	},
	{
		"tm" : 1720831797990,
		"x" : 25,
		"y" : 743
	},
	{
		"tm" : 1720831798419,
		"x" : 22,
		"y" : 746
	},
	{
		"tm" : 1720831798833,
		"x" : 19,
		"y" : 749
	},
	{
		"tm" : 1720831799239,
		"x" : 19,
		"y" : 752
	},
	{
		"tm" : 1720831799648,
		"x" : 19,
		"y" : 755
	},
	{
		"tm" : 1720831800043,
		"x" : 19,
		"y" : 758
	},
	{
		"tm" : 1720831800466,
		"x" : 19,
		"y" : 761
	},
	{
		"tm" : 1720831800861,
		"x" : 19,
		"y" : 764
	},
	{
		"tm" : 1720831801285,
		"x" : 19,
		"y" : 767
	},
	{
		"tm" : 1720831801682,
		"x" : 19,
		"y" : 770
	},
	{
		"tm" : 1720831802092,
		"x" : 19,
		"y" : 773
	},
	{
		"tm" : 1720831802504,
		"x" : 19,
		"y" : 776
	},
	{
		"tm" : 1720831802920,
		"x" : 19,
		"y" : 779
	},
	{
		"tm" : 1720831803318,
		"x" : 19,
		"y" : 782
	},
	{
		"tm" : 1720831803723,
		"x" : 19,
		"y" : 785
	},
	{
		"tm" : 1720831804134,
		"x" : 19,
		"y" : 788
	},
	{
		"tm" : 1720831804540,
		"x" : 19,
		"y" : 791
	},
	{
		"tm" : 1720831804940,
		"x" : 19,
		"y" : 794
	},
	{
		"tm" : 1720831805345,
		"x" : 19,
		"y" : 797
	},
	{
		"tm" : 1720831805752,
		"x" : 19,
		"y" : 800
	},
	{
		"tm" : 1720831806160,
		"x" : 19,
		"y" : 803
	},
	{
		"tm" : 1720831806566,
		"x" : 19,
		"y" : 806
	},
	{
		"tm" : 1720831806970,
		"x" : 19,
		"y" : 809
	},
	{
		"tm" : 1720831807374,
		"x" : 19,
		"y" : 812
	},
	{
		"tm" : 1720831807780,
		"x" : 19,
		"y" : 815
	},
	{
		"tm" : 1720831808190,
		"x" : 19,
		"y" : 818
	},
	{
		"tm" : 1720831808588,
		"x" : 19,
		"y" : 821
	},
	{
		"tm" : 1720831809012,
		"x" : 19,
		"y" : 824
	},
	{
		"tm" : 1720831809412,
		"x" : 22,
		"y" : 827
	},
	{
		"tm" : 1720831809816,
		"x" : 22,
		"y" : 830
	},
	{
		"tm" : 1720831810218,
		"x" : 22,
		"y" : 833
	},
	{
		"tm" : 1720831810622,
		"x" : 22,
		"y" : 836
	},
	{
		"tm" : 1720831811026,
		"x" : 22,
		"y" : 839
	},
	{
		"tm" : 1720831811430,
		"x" : 25,
		"y" : 842
	},
	{
		"tm" : 1720831811839,
		"x" : 28,
		"y" : 845
	},
	{
		"tm" : 1720831812243,
		"x" : 31,
		"y" : 848
	},
	{
		"tm" : 1720831812644,
		"x" : 34,
		"y" : 851
	},
	{
		"tm" : 1720831813047,
		"x" : 37,
		"y" : 854
	},
	{
		"tm" : 1720831813439,
		"x" : 37,
		"y" : 857
	},
	{
		"tm" : 1720831813852,
		"x" : 40,
		"y" : 860
	},
	{
		"tm" : 1720831814271,
		"x" : 40,
		"y" : 863
	},
	{
		"tm" : 1720831814675,
		"x" : 40,
		"y" : 866
	},
	{
		"tm" : 1720831815082,
		"x" : 40,
		"y" : 869
	},
	{
		"tm" : 1720831815481,
		"x" : 40,
		"y" : 872
	},
	{
		"tm" : 1720831815896,
		"x" : 40,
		"y" : 875
	},
	{
		"tm" : 1720831816294,
		"x" : 40,
		"y" : 878
	},
	{
		"tm" : 1720831816691,
		"x" : 40,
		"y" : 881
	},
	{
		"tm" : 1720831817103,
		"x" : 40,
		"y" : 884
	},
	{
		"tm" : 1720831817522,
		"x" : 40,
		"y" : 887
	},
	{
		"tm" : 1720831817920,
		"x" : 40,
		"y" : 890
	},
	{
		"tm" : 1720831818337,
		"x" : 40,
		"y" : 893
	},
	{
		"tm" : 1720831818735,
		"x" : 40,
		"y" : 896
	},
	{
		"tm" : 1720831819146,
		"x" : 40,
		"y" : 899
	},
	{
		"tm" : 1720831819561,
		"x" : 40,
		"y" : 902
	},
	{
		"tm" : 1720831819969,
		"x" : 40,
		"y" : 905
	},
	{
		"tm" : 1720831820366,
		"x" : 40,
		"y" : 908
	},
	{
		"tm" : 1720831820777,
		"x" : 40,
		"y" : 911
	},
	{
		"tm" : 1720831821188,
		"x" : 40,
		"y" : 914
	},
	{
		"tm" : 1720831821605,
		"x" : 40,
		"y" : 917
	},
	{
		"tm" : 1720831822018,
		"x" : 40,
		"y" : 920
	},
	{
		"tm" : 1720831822432,
		"x" : 40,
		"y" : 923
	},
	{
		"tm" : 1720831822842,
		"x" : 40,
		"y" : 926
	},
	{
		"tm" : 1720831823252,
		"x" : 40,
		"y" : 929
	},
	{
		"tm" : 1720831823672,
		"x" : 40,
		"y" : 932
	},
	{
		"tm" : 1720831824076,
		"x" : 40,
		"y" : 935
	},
	{
		"tm" : 1720831824470,
		"x" : 40,
		"y" : 938
	},
	{
		"tm" : 1720831824882,
		"x" : 40,
		"y" : 941
	},
	{
		"tm" : 1720831825294,
		"x" : 40,
		"y" : 944
	},
	{
		"tm" : 1720831825708,
		"x" : 40,
		"y" : 947
	},
	{
		"tm" : 1720831826121,
		"x" : 40,
		"y" : 950
	},
	{
		"tm" : 1720831826535,
		"x" : 40,
		"y" : 953
	},
	{
		"tm" : 1720831826950,
		"x" : 40,
		"y" : 956
	},
	{
		"tm" : 1720831827364,
		"x" : 40,
		"y" : 959
	},
	{
		"tm" : 1720831827779,
		"x" : 40,
		"y" : 962
	},
	{
		"tm" : 1720831828192,
		"x" : 40,
		"y" : 965
	},
	{
		"tm" : 1720831828605,
		"x" : 40,
		"y" : 968
	},
	{
		"tm" : 1720831829019,
		"x" : 40,
		"y" : 971
	},
	{
		"tm" : 1720831829434,
		"x" : 40,
		"y" : 974
	},
	{
		"tm" : 1720831829848,
		"x" : 40,
		"y" : 977
	},
	{
		"tm" : 1720831830262,
		"x" : 40,
		"y" : 980
	},
	{
		"tm" : 1720831830693,
		"x" : 37,
		"y" : 983
	},
	{
		"tm" : 1720831830836,
		"x" : 37,
		"y" : 984
	}
]